msx_serial/__init__.py
msx_serial/__main__.py
msx_serial/_version.py
msx_serial/commands/__init__.py
msx_serial/commands/command_types.py
msx_serial/commands/handler.py
msx_serial/commands/performance_commands.py
msx_serial/common/__init__.py
msx_serial/common/cache_manager.py
msx_serial/common/color_output.py
msx_serial/common/config_manager.py
msx_serial/common/profiler.py
msx_serial/completion/basic_filesystem.py
msx_serial/completion/dos_filesystem.py
msx_serial/completion/iot_loader.py
msx_serial/completion/keyword_loader.py
msx_serial/completion/completers/__init__.py
msx_serial/completion/completers/base.py
msx_serial/completion/completers/basic_completer.py
msx_serial/completion/completers/command_completer.py
msx_serial/completion/completers/dos_completer.py
msx_serial/completion/completers/help_completer.py
msx_serial/completion/completers/iot_completer.py
msx_serial/completion/completers/special_completer.py
msx_serial/connection/base.py
msx_serial/connection/config_factory.py
msx_serial/connection/connection.py
msx_serial/connection/dummy.py
msx_serial/connection/manager.py
msx_serial/connection/serial.py
msx_serial/connection/telnet.py
msx_serial/connection/uri_parser.py
msx_serial/core/__init__.py
msx_serial/core/data_processor.py
msx_serial/core/msx_session.py
msx_serial/data/__init__.py
msx_serial/data/dos_commands.yml
msx_serial/data/iot_basic_nodes.yml
msx_serial/data/msx_keywords.yml
msx_serial/display/__init__.py
msx_serial/display/basic_display.py
msx_serial/display/enhanced_display.py
msx_serial/io/__init__.py
msx_serial/io/data_sender.py
msx_serial/io/input_session.py
msx_serial/io/user_interface.py
msx_serial/man/ABS.3
msx_serial/man/AND.3
msx_serial/man/ASC.3
msx_serial/man/ATN.3
msx_serial/man/AUTO.3
msx_serial/man/BASE.3
msx_serial/man/BEEP.3
msx_serial/man/BIN$.3
msx_serial/man/BLOAD(1).3
msx_serial/man/BLOAD(2).3
msx_serial/man/BSAVE(1).3
msx_serial/man/BSAVE(2).3
msx_serial/man/CALL AKCNV.3
msx_serial/man/CALL ANK.3
msx_serial-0.2.26.dist-info/licenses/LICENSE
msx_serial-0.2.26.dist-info/METADATA
msx_serial-0.2.26.dist-info/WHEEL
msx_serial-0.2.26.dist-info/entry_points.txt
msx_serial-0.2.26.dist-info/top_level.txt
msx_serial-0.2.26.dist-info/RECORD
