Metadata-Version: 2.4
Name: msx-serial
Version: 0.2.26
Summary: MSXシリアルターミナル
Author-email: yamamo-to <humorum@gmail.com>
Project-URL: Repository, https://github.com/yamamo-to/msx-serial
Project-URL: Issue, https://github.com/yamamo-to/msx-serial/issues
Classifier: Development Status :: 4 - Beta
Classifier: Intended Audience :: Developers
Classifier: Programming Language :: Python :: 3
Classifier: Programming Language :: Python :: 3.9
Classifier: Programming Language :: Python :: 3.10
Classifier: Programming Language :: Python :: 3.11
Classifier: Programming Language :: Python :: 3.12
Classifier: Topic :: Software Development :: Libraries :: Python Modules
Requires-Python: >=3.9
License-File: LICENSE
Requires-Dist: colorama
Requires-Dist: prompt-toolkit
Requires-Dist: pyserial
Requires-Dist: PyYAML
Requires-Dist: chardet
Requires-Dist: msx-charset
Requires-Dist: tqdm
Requires-Dist: standard-telnetlib
Requires-Dist: jinja2
Provides-Extra: dev
Requires-Dist: pytest>=7.0; extra == "dev"
Requires-Dist: pytest-cov>=4.0; extra == "dev"
Requires-Dist: flake8>=6.0; extra == "dev"
Requires-Dist: mypy>=1.0; extra == "dev"
Requires-Dist: build>=1.0; extra == "dev"
Requires-Dist: twine>=4.0; extra == "dev"
Requires-Dist: types-colorama; extra == "dev"
Requires-Dist: types-PyYAML; extra == "dev"
Requires-Dist: types-pyserial; extra == "dev"
Requires-Dist: types-tqdm; extra == "dev"
Dynamic: license-file
